qaviton_pip/__init__.py
qaviton_pip/pip_wrapper.py
qaviton_pip-2019.9.29.8.1.45.50215.dist-info/LICENSE
qaviton_pip-2019.9.29.8.1.45.50215.dist-info/METADATA
qaviton_pip-2019.9.29.8.1.45.50215.dist-info/WHEEL
qaviton_pip-2019.9.29.8.1.45.50215.dist-info/top_level.txt
qaviton_pip-2019.9.29.8.1.45.50215.dist-info/RECORD
