Metadata-Version: 2.1
Name: qaviton-pip
Version: 2019.9.29.8.1.45.50215
Summary: qaviton pip
Home-page: https://github.com/qaviton/qaviton_pip.git
Author: yehonadav
Author-email: yonadav.barilan@gmail.com
License: apache-2.0
Platform: UNKNOWN
Classifier: Programming Language :: Python :: 3.6
Requires-Dist: qaviton-processes (>=2019.9.4.12.58.22.283354)
